Metadata-Version: 2.1
Name: flatway
Version: 2.0.0
Summary: Python package for flatting of list, tuple or dictionary.
Home-page: https://github.com/Paiman-Rasoli/flatway
Author: Paiman Rasoli
Author-email: paimanrasoli789@gmail.com
License: MIT
Project-URL: Source, https://github.com/Paiman-Rasoli/flatway
Keywords: flat,flatten,flat list,flat tuple,flatway,flatdict
Classifier: Programming Language :: Python :: 3
Classifier: License :: OSI Approved :: MIT License
Classifier: Operating System :: OS Independent
Requires-Python: >=3.5
Requires-Dist: pytest
